motra/__init__.py
motra/m2m.py
motra/m2t.py
motra/trace/TransformationTrace.py
motra/trace/__init__.py
motra-0.1.1.dist-info/LICENSE
motra-0.1.1.dist-info/METADATA
motra-0.1.1.dist-info/WHEEL
motra-0.1.1.dist-info/top_level.txt
motra-0.1.1.dist-info/RECORD
