Metadata-Version: 2.1
Name: motra
Version: 0.1.1
Summary: M2M and M2T Models Transformations framework for PyEcore
Home-page: https://github.com/pyecore/motra
Author: Vincent Aranega
Author-email: vincent.aranega@gmail.com
License: BSD 3-Clause
Keywords: model metamodel MDE M2M M2T traceability transformation
Platform: UNKNOWN
Classifier: Development Status :: 3 - Alpha
Classifier: Programming Language :: Python
Classifier: Programming Language :: Python :: 3.5
Classifier: Programming Language :: Python :: 3.6
Classifier: Programming Language :: Python :: 3.7
Classifier: Programming Language :: Python :: 3.8
Classifier: Programming Language :: Python :: 3.9
Classifier: Operating System :: OS Independent
Classifier: Intended Audience :: Developers
Classifier: Topic :: Software Development
Classifier: Topic :: Software Development :: Libraries
Classifier: License :: OSI Approved :: BSD License
License-File: LICENSE
Requires-Dist: pyecore
Requires-Dist: Mako
